arg/__init__.py
arg-0.0.1.dist-info/METADATA
arg-0.0.1.dist-info/RECORD
arg-0.0.1.dist-info/WHEEL
arg-0.0.1.dist-info/top_level.txt
